wenv/__init__.py
wenv/__main__.py
wenv/_core/__init__.py
wenv/_core/config.py
wenv/_core/const.py
wenv/_core/env.py
wenv/_core/errors.py
wenv/_core/paths.py
wenv/_core/pythonversion.py
wenv/_core/source.py
wenv/_core/typeguard.py
wenv-0.5.1.dist-info/entry_points.txt
wenv-0.5.1.dist-info/LICENSE
wenv-0.5.1.dist-info/WHEEL
wenv-0.5.1.dist-info/METADATA
wenv-0.5.1.dist-info/RECORD
