Metadata-Version: 2.1
Name: wenv
Version: 0.5.1
Summary: Running Python on Wine
Keywords: wine,cross platform
Author-email: "Sebastian M. Ernst" <ernst@pleiszenburg.de>
Maintainer-email: "Sebastian M. Ernst" <ernst@pleiszenburg.de>
Requires-Python: >=3.7
Classifier: Development Status :: 4 - Beta
Classifier: Intended Audience :: Developers
Classifier: Intended Audience :: Information Technology
Classifier: Intended Audience :: Science/Research
Classifier: Intended Audience :: System Administrators
Classifier: License :: OSI Approved :: GNU Lesser General Public License v2 (LGPLv2)
Classifier: Operating System :: MacOS
Classifier: Operating System :: POSIX :: BSD
Classifier: Operating System :: POSIX :: Linux
Classifier: Programming Language :: Python :: 3
Classifier: Programming Language :: Python :: 3.7
Classifier: Programming Language :: Python :: 3.8
Classifier: Programming Language :: Python :: 3.9
Classifier: Programming Language :: Python :: 3.10
Classifier: Programming Language :: Python :: 3 :: Only
Classifier: Programming Language :: Python :: Implementation :: CPython
Classifier: Topic :: Scientific/Engineering
Classifier: Topic :: Software Development
Classifier: Topic :: System :: Operating System
Classifier: Topic :: System :: Operating System Kernels
Classifier: Topic :: Utilities
Requires-Dist: black ; extra == "dev"
Requires-Dist: pytest ; extra == "dev"
Requires-Dist: coverage[toml] ; extra == "dev"
Requires-Dist: pytest-cov ; extra == "dev"
Requires-Dist: python-lsp-server[all] ; extra == "dev"
Requires-Dist: Sphinx ; extra == "dev"
Requires-Dist: sphinx_rtd_theme ; extra == "dev"
Requires-Dist: sphinx-autodoc-typehints ; extra == "dev"
Requires-Dist: typeguard ; extra == "dev"
Requires-Dist: myst-parser ; extra == "dev"
Requires-Dist: twine ; extra == "dev"
Project-URL: Documentation, https://wenv.readthedocs.io/en/latest/
Project-URL: Home, https://github.com/pleiszenburg/wenv
Project-URL: Source, https://github.com/pleiszenburg/wenv
Provides-Extra: dev
